LICENSE.txt
README.md
setup.cfg
setup.py
divia_api/__init__.py
divia_api/api.py
divia_api/exceptions.py
divia_api/line.py
divia_api/normalize_characters.py
divia_api/stop.py
divia_api/velodi.py
divia_api.egg-info/PKG-INFO
divia_api.egg-info/SOURCES.txt
divia_api.egg-info/dependency_links.txt
divia_api.egg-info/requires.txt
divia_api.egg-info/top_level.txt