Metadata-Version: 2.1
Name: divia-api
Version: 2.0
Summary: divia_api is a Python library that allows to retrieve the timetable of Divia’s bus and tramways, along with some infos about DiviaVélodi bikes, straight from a Python script.
Home-page: https://github.com/filau/python_divia_api
Author: Firmin Launay
Author-email: hey@firminlaunay.me
License: LGPL-3.0
Download-URL: https://github.com/filau/python_divia_api/archive/refs/tags/2.0.tar.gz
Keywords: divia,api,firmin,launay,dijon,bus,tram
Platform: UNKNOWN
Classifier: Development Status :: 5 - Production/Stable
Classifier: Intended Audience :: Developers
Classifier: Topic :: Software Development :: Build Tools
Classifier: License :: OSI Approved :: GNU Lesser General Public License v3 (LGPLv3)
Classifier: Programming Language :: Python :: 3.6
Classifier: Programming Language :: Python :: 3.7
Classifier: Programming Language :: Python :: 3.8
Classifier: Programming Language :: Python :: 3.9
License-File: LICENSE.txt
